sauronblp/__init__.py
sauronblp/client.py
sauronblp-1.0.0.0.dist-info/METADATA
sauronblp-1.0.0.0.dist-info/WHEEL
sauronblp-1.0.0.0.dist-info/top_level.txt
sauronblp-1.0.0.0.dist-info/RECORD
