Metadata-Version: 2.1
Name: sauronblp
Version: 1.0.0.0
Summary: blp client for sauron users
Home-page: https://sauron9973.blogspot.com
Author: sauron9973
Author-email: sauron9973@gmail.com
License: MIT
Platform: UNKNOWN
Requires-Python: >=3
